{
    "domain": "course_module",
    "skintype": "score",
    "skinname": "bundled",
    "title": "discrete grade-based score",
    "description": "Points award for passing key grade thresholds",
    "css": ".sub-tile.skin-tile .skin-text {font-size:200%;} \n .sub-tile.skin-tile .skin-text.score{display: block;position: absolute;left: 59%;bottom: 38%;font-size:150%;font-weight:bold;} \n .sub-tile.skin-tile .skin-text.score::after{content: \"pts\";font-size:100%;font-weight:normal;}\n ",
    "steps": [
        {
            "threshold": 0,
            "score": 0,
            "text": "",
            "css": "",
            "background": "default-user-skins\/cup-score\/cup-score-2-1"
        },
        {
            "threshold": 50,
            "score": "50",
            "text": "",
            "css": "",
            "background": "default-user-skins\/cup-score\/cup-score-2-2"
        },
        {
            "threshold": 80,
            "score": 100,
            "text": "",
            "css": ".skin-text.threshold{display:none;}\n .skin-text.score{bottom: 39%}",
            "background": "default-user-skins\/cup-score\/cup-score-2-3"
        }
    ]
}
